rst/__init__.py
rst/autocomplete.py
rst/conn_handler.py
rst/lang_handler.py
rst/listener_handler.py
rst/ngrok_handler.py
rst/rst.py
reverse_shell_tool-1.0.3.dist-info/LICENSE
reverse_shell_tool-1.0.3.dist-info/METADATA
reverse_shell_tool-1.0.3.dist-info/WHEEL
reverse_shell_tool-1.0.3.dist-info/entry_points.txt
reverse_shell_tool-1.0.3.dist-info/top_level.txt
reverse_shell_tool-1.0.3.dist-info/RECORD
